AngularjsXuexiBijiCheckcheckzz/README.md
AngularjsXuexiBijiCheckcheckzz/__init__.py
AngularjsXuexiBijiCheckcheckzz/__main__.py
AngularjsXuexiBijiCheckcheckzz/file.epub
AngularjsXuexiBijiCheckcheckzz/index.html
AngularjsXuexiBijiCheckcheckzz/css/__init__.py
AngularjsXuexiBijiCheckcheckzz/css/annotations.css
AngularjsXuexiBijiCheckcheckzz/css/main.css
AngularjsXuexiBijiCheckcheckzz/css/normalize.css
AngularjsXuexiBijiCheckcheckzz/css/popup.css
AngularjsXuexiBijiCheckcheckzz/font/__init__.py
AngularjsXuexiBijiCheckcheckzz/font/fontello.eot
AngularjsXuexiBijiCheckcheckzz/font/fontello.svg
AngularjsXuexiBijiCheckcheckzz/font/fontello.ttf
AngularjsXuexiBijiCheckcheckzz/font/fontello.woff
AngularjsXuexiBijiCheckcheckzz/img/__init__.py
AngularjsXuexiBijiCheckcheckzz/img/annotator-glyph-sprite.png
AngularjsXuexiBijiCheckcheckzz/img/annotator-icon-sprite.png
AngularjsXuexiBijiCheckcheckzz/img/apple-touch-icon.png
AngularjsXuexiBijiCheckcheckzz/img/cancelfullscreen.png
AngularjsXuexiBijiCheckcheckzz/img/close.png
AngularjsXuexiBijiCheckcheckzz/img/fullscreen.png
AngularjsXuexiBijiCheckcheckzz/img/loader.gif
AngularjsXuexiBijiCheckcheckzz/img/menu-icon.png
AngularjsXuexiBijiCheckcheckzz/img/save.png
AngularjsXuexiBijiCheckcheckzz/img/saved.png
AngularjsXuexiBijiCheckcheckzz/img/settings-s.png
AngularjsXuexiBijiCheckcheckzz/img/settings.png
AngularjsXuexiBijiCheckcheckzz/img/star.png
AngularjsXuexiBijiCheckcheckzz/js/__init__.py
AngularjsXuexiBijiCheckcheckzz/js/epub.js
AngularjsXuexiBijiCheckcheckzz/js/epub.min.js
AngularjsXuexiBijiCheckcheckzz/js/epub.min.map
AngularjsXuexiBijiCheckcheckzz/js/hooks.min.js
AngularjsXuexiBijiCheckcheckzz/js/hooks.min.map
AngularjsXuexiBijiCheckcheckzz/js/reader.js
AngularjsXuexiBijiCheckcheckzz/js/reader.js.map
AngularjsXuexiBijiCheckcheckzz/js/reader.min.js
AngularjsXuexiBijiCheckcheckzz/js/reader.min.map
AngularjsXuexiBijiCheckcheckzz/js/hooks/__init__.py
AngularjsXuexiBijiCheckcheckzz/js/hooks/extensions/__init__.py
angularjs_xuexi_biji_checkcheckzz-2024.3.3.0.dist-info/METADATA
angularjs_xuexi_biji_checkcheckzz-2024.3.3.0.dist-info/WHEEL
angularjs_xuexi_biji_checkcheckzz-2024.3.3.0.dist-info/entry_points.txt
angularjs_xuexi_biji_checkcheckzz-2024.3.3.0.dist-info/top_level.txt
angularjs_xuexi_biji_checkcheckzz-2024.3.3.0.dist-info/RECORD
